{
	"credit": "Made with Blockbench",
	"texture_size": [32, 32],
	"textures": {
		"1": "expandeddelight:block/cheese_wheel_top",
		"2": "expandeddelight:block/cheese_wheel_side",
		"particle": "expandeddelight:block/cheese_wheel_side"
	},
	"elements": [
		{
			"from": [1, 0, 1],
			"to": [15, 8, 15],
			"faces": {
				"north": {"uv": [1, 8, 15, 16], "texture": "#2"},
				"east": {"uv": [1, 8, 15, 16], "texture": "#2"},
				"south": {"uv": [1, 8, 15, 16], "texture": "#2"},
				"west": {"uv": [1, 8, 15, 16], "texture": "#2"},
				"up": {"uv": [1, 1, 15, 15], "texture": "#1"},
				"down": {"uv": [1, 15, 15, 1], "rotation": 90, "texture": "#1", "cullface": "down"}
			}
		}
	]
}